my_datasets/__init__.py
my_datasets/iris.py
my_datasets/data/Electric_Vehicle_Data.csv
my_datasets/data/Iris.csv
my_datasets/data/Most Streamed Spotify Songs 2024.csv
my_datasets/data/flight_data_2018_2024.csv
my_datasets/data/online_course_engagement_data.csv
my_unique_datasets_library-0.9.9.dist-info/METADATA
my_unique_datasets_library-0.9.9.dist-info/WHEEL
my_unique_datasets_library-0.9.9.dist-info/top_level.txt
my_unique_datasets_library-0.9.9.dist-info/RECORD
