Metadata-Version: 2.1
Name: my_unique_datasets_library
Version: 0.9.9
Summary: A library that provides predefined datasets.
Author: ravishankar
Author-email: your.email@example.com
Keywords: datasets,iris,data science
Classifier: Programming Language :: Python :: 3
Classifier: License :: OSI Approved :: MIT License
Classifier: Operating System :: OS Independent
Requires-Dist: pandas
Requires-Dist: tensorflow
Requires-Dist: Pillow
